{ "items": [ { "card": { "type": "list_card", "cells": [ { "type": "left_right_cell_view", "divider": { "style": "default", "size": "d3" }, "paddings": { "left": "8x", "top": "4x", "right": "8x", "bottom": "4x" }, "left": { "type": "simple_left_view", "texts": { "title": { "text": "", "typeface": "body1", "text_color": "default", "max_lines": 0 } } }, "right": { "type": "disclosure_right_view", "margins": { "top": "8x", "right": "4x", "bottom": "8x" }, "vertical_gravity": "top" }, "actions": [ { "type": "text", "text": "Открой города" } ] } ] } } ] }
